kw3pan/__init__.py
kw3pan/web3_wrapper.py
kw3pan/pancakeswap/__init__.py
kw3pan/pancakeswap/constants.py
kw3pan/pancakeswap/factory/__init__.py
kw3pan/pancakeswap/factory/busd/__init__.py
kw3pan/pancakeswap/factory/busd/pancakeswap_busd_factory.py
kw3pan/pancakeswap/factory/core/__init__.py
kw3pan/pancakeswap/factory/core/_abi.py
kw3pan/pancakeswap/factory/core/pancakeswap_factory.py
kw3pan/pancakeswap/factory/wbnb/__init__.py
kw3pan/pancakeswap/factory/wbnb/pancakeswap_wbnb_factory.py
kw3pan/pancakeswap/liquidity_pool/__init__.py
kw3pan/pancakeswap/liquidity_pool/busd/__init__.py
kw3pan/pancakeswap/liquidity_pool/busd/pancakeswap_busd_liquidity_pool.py
kw3pan/pancakeswap/liquidity_pool/busd/reserves_busd.py
kw3pan/pancakeswap/liquidity_pool/core/__init__.py
kw3pan/pancakeswap/liquidity_pool/core/_abi.py
kw3pan/pancakeswap/liquidity_pool/core/pancakeswap_liquidity_pool.py
kw3pan/pancakeswap/liquidity_pool/core/reserves.py
kw3pan/pancakeswap/liquidity_pool/wbnb/__init__.py
kw3pan/pancakeswap/liquidity_pool/wbnb/pancakeswap_wbnb_liquidity_pool.py
kw3pan/pancakeswap/liquidity_pool/wbnb/reserves_wbnb.py
kw3pan/pancakeswap/liquidity_pool/wbnb_busd/__init__.py
kw3pan/pancakeswap/liquidity_pool/wbnb_busd/pancakeswap_wbnb_busd_liquidity_pool.py
kw3pan/pancakeswap/liquidity_pool/wbnb_busd/reserves_wbnb_busd.py
kw3pan-0.0.8.dist-info/LICENSE
kw3pan-0.0.8.dist-info/METADATA
kw3pan-0.0.8.dist-info/WHEEL
kw3pan-0.0.8.dist-info/top_level.txt
kw3pan-0.0.8.dist-info/RECORD
