Metadata-Version: 2.1
Name: kw3pan
Version: 0.0.8
Summary: kw3pan
Home-page: https://github.com/kkristof200/py_web3_pancakeswap
Author: Kristóf-Attila Kovács
License: UNKNOWN
Platform: UNKNOWN
Classifier: Programming Language :: Python :: 3.4
Classifier: Programming Language :: Python :: 3.5
Classifier: Programming Language :: Python :: 3.6
Classifier: Programming Language :: Python :: 3.7
Classifier: Programming Language :: Python :: 3.8
Classifier: Programming Language :: Python :: 3.9
Classifier: License :: OSI Approved :: MIT License
Classifier: Operating System :: OS Independent
Requires-Python: >=3.4
Requires-Dist: jsoncodable (>=0.1.2)
Requires-Dist: kw3 (>=0.0.6)
